pydtnn/__init__.py
pydtnn/layer_base.py
pydtnn/model.py
pydtnn/parser.py
pydtnn/pydtnn_benchmark.py
pydtnn/activations/activation.py
pydtnn/activations/arctanh.py
pydtnn/activations/leaky_relu.py
pydtnn/activations/log.py
pydtnn/activations/relu.py
pydtnn/activations/relu6.py
pydtnn/activations/sigmoid.py
pydtnn/activations/softmax.py
pydtnn/activations/tanh.py
pydtnn/backends/__init__.py
pydtnn/backends/cpu/activations/activation.py
pydtnn/backends/cpu/activations/arctanh.py
pydtnn/backends/cpu/activations/leaky_relu.py
pydtnn/backends/cpu/activations/log.py
pydtnn/backends/cpu/activations/relu.py
pydtnn/backends/cpu/activations/relu6.py
pydtnn/backends/cpu/activations/sigmoid.py
pydtnn/backends/cpu/activations/softmax.py
pydtnn/backends/cpu/activations/tanh.py
pydtnn/backends/cpu/layers/adaptive_average_pool_2d.py
pydtnn/backends/cpu/layers/addition_block.py
pydtnn/backends/cpu/layers/average_pool_2d.py
pydtnn/backends/cpu/layers/batch_normalization.py
pydtnn/backends/cpu/layers/batch_normalization_relu.py
pydtnn/backends/cpu/layers/concatenation_block.py
pydtnn/backends/cpu/layers/conv_2d.py
pydtnn/backends/cpu/layers/conv_2d_batch_normalization.py
pydtnn/backends/cpu/layers/conv_2d_batch_normalization_relu.py
pydtnn/backends/cpu/layers/conv_2d_relu.py
pydtnn/backends/cpu/layers/decoder.py
pydtnn/backends/cpu/layers/dropout.py
pydtnn/backends/cpu/layers/encoder.py
pydtnn/backends/cpu/layers/encoder_decoder.py
pydtnn/backends/cpu/layers/fc.py
pydtnn/backends/cpu/layers/feed_forward.py
pydtnn/backends/cpu/layers/flatten.py
pydtnn/backends/cpu/layers/input.py
pydtnn/backends/cpu/layers/layer.py
pydtnn/backends/cpu/layers/layer_normalization.py
pydtnn/backends/cpu/layers/max_pool_2d.py
pydtnn/backends/cpu/layers/multi_head_attention.py
pydtnn/backends/cpu/layers/multiplication.py
pydtnn/backends/cpu/layers/scalar.py
pydtnn/backends/cpu/layers/abstract/block_layer.py
pydtnn/backends/cpu/layers/abstract/conv_2d_standard.py
pydtnn-2.0.0.dist-info/licenses/LICENSE
pydtnn-2.0.0.dist-info/METADATA
pydtnn-2.0.0.dist-info/WHEEL
pydtnn-2.0.0.dist-info/entry_points.txt
pydtnn-2.0.0.dist-info/top_level.txt
pydtnn-2.0.0.dist-info/RECORD
