Metadata-Version: 2.4
Name: pydtnn
Version: 2.0.0
Summary: Python Distributed Training of Neural Networks
Author-email: Adrián Castelló Gimeno <adcastel@uji.es>, Andrés Enrique Tomás Domínguez <antodo@upv.es>, Enrique Salvador Quintana Ortí <quintana@uji.es>, Jose Ignacio Mestre Miravet <jmiravet@uji.es>, Manuel Francisco Dolz Zaragozá <dolzm@uji.es>, Mar Catalán Carbó <catalama@uji.es>, Miguel Pardo Navarro <mipardo@uji.es>, Miguel Ángel Prosper Quirós <mprosper@uji.es>, Paul Ximo Pluijter Izquierdo <pluijter@uji.es>, Sergio Barrachina Mir <barrachi@uji.es>
Maintainer-email: Manuel Francisco Dolz Zaragozá <dolzm@uji.es>
License-Expression: GPL-3.0-or-later
Project-URL: Homepage, https://github.com/hpca-uji/PyDTNN
Project-URL: Repository, https://github.com/hpca-uji/PyDTNN.git
Keywords: Deep neural networks,Distributed parallel training,Python
Classifier: Development Status :: 5 - Production/Stable
Classifier: Intended Audience :: Science/Research
Classifier: Programming Language :: Python :: 3 :: Only
Classifier: Programming Language :: Python :: 3.13
Classifier: Topic :: Scientific/Engineering
Classifier: Topic :: Scientific/Engineering :: Artificial Intelligence
Requires-Python: >=3.13
License-File: LICENSE
Requires-Dist: cython>=0.29.21
Requires-Dist: numpy>=1.19.4
Requires-Dist: matplotlib>=3.3.3
Requires-Dist: prettytable>=2.1.0
Requires-Dist: rich>=9.9.0
Requires-Dist: scikit-image>=0.17.2
Requires-Dist: scipy>=1.5.4
Requires-Dist: tqdm>=4.55.0
Requires-Dist: rapidgzip>=0.15.2
Provides-Extra: cuda
Requires-Dist: pycuda>=2021.1; extra == "cuda"
Requires-Dist: scikit-cuda>=0.5.3; extra == "cuda"
Requires-Dist: nvidia-cudnn>=8.1.1.33; extra == "cuda"
Provides-Extra: mpi
Requires-Dist: net-queue>=0.1.0; extra == "mpi"
Requires-Dist: pympi>=0.1.0; extra == "mpi"
Requires-Dist: mpi4py>=4.1.0; extra == "mpi"
Provides-Extra: fhe
Requires-Dist: openfhe>=1.4.0; extra == "fhe"
Requires-Dist: tenseal>=0.3.16; extra == "fhe"
Provides-Extra: test
Requires-Dist: torch>=2.6.0; extra == "test"
Requires-Dist: torchvision>=0.21.0; extra == "test"
Provides-Extra: profile
Requires-Dist: memray>=1.19.1; extra == "profile"
Provides-Extra: pypi
Requires-Dist: build>=1.3.0; extra == "pypi"
Requires-Dist: auditwheel>=6.5.1; extra == "pypi"
Requires-Dist: twine>=6.2.0; extra == "pypi"
Provides-Extra: dev
Requires-Dist: autopep8>=2.3.1; extra == "dev"
Requires-Dist: flake8>=7.1.1; extra == "dev"
Requires-Dist: flake8-docstrings>=1.7.0; extra == "dev"
Requires-Dist: mccabe>=0.7.0; extra == "dev"
Requires-Dist: pep8-naming>=0.14.1; extra == "dev"
Requires-Dist: pipdeptree>=2.23.1; extra == "dev"
Requires-Dist: pycodestyle>=2.12.1; extra == "dev"
Requires-Dist: pydocstyle>=6.3.0; extra == "dev"
Requires-Dist: pyflakes>=3.2.0; extra == "dev"
Dynamic: license-file
